shmutils/_shmutils.abi3.so
shmutils/ffibuilder.py
shmutils/lock.py
shmutils/posix.py
shmutils/__init__.py
shmutils/typing.py
shmutils/exceptions.py
shmutils/errors.py
shmutils/utils.py
shmutils/mmap.py
shmutils/shm.py
shmutils-0.0.2.dist-info/WHEEL
shmutils-0.0.2.dist-info/top_level.txt
shmutils-0.0.2.dist-info/LICENSE
shmutils-0.0.2.dist-info/METADATA
shmutils-0.0.2.dist-info/RECORD
