Metadata-Version: 2.1
Name: shmutils
Version: 0.0.2
Summary: Shared memory structures
Home-page: https://github.com/autumnjolitz/shmutils
Author: Autumn Jolitz
License: BSD 3-Clause License
Keywords: shm,shared,memory,posix,mmap,munmap,shm_open,shm_unlink,pickle,cffi,cdata,shared,heap
Platform: posix
Classifier: Development Status :: 3 - Alpha
Classifier: License :: OSI Approved :: BSD License
Classifier: Operating System :: MacOS :: MacOS X
Classifier: Operating System :: POSIX :: BSD
Classifier: Operating System :: POSIX :: Linux
Classifier: Topic :: Software Development :: Libraries :: Python Modules
Classifier: Topic :: System :: Hardware :: Symmetric Multi-processing
Provides-Extra: test
License-File: LICENSE
